{
  "items": [
    { "title": "GitHub", "imageUrl": "/icons/icons-github-icon.webp", "link": "#" },
    { "title": "CloudSploit", "imageUrl": "/partners/partner-cloudsploit.webp", "link": "#" },
    { "title": "Coding Blocks", "imageUrl": "/partners/partner-coding-blocks.webp", "link": "#" },
    { "title": "Fold", "imageUrl": "/partners/partner-fold.webp", "link": "#" },
    { "title": "Slack", "imageUrl": "/partners/partner-slack.webp", "link": "#" },
    { "title": "Devfolio", "imageUrl": "/partners/partner-devfolio.webp", "link": "#" },
    { "title": "Matic", "imageUrl": "/partners/partner-matic.webp", "link": "#" },
    { "title": "Wolfram Language", "imageUrl": "/partners/partner-wolfram-language.webp", "link": "#" },
    { "title": "Bugsee", "imageUrl": "/partners/partner-bugsee.webp", "link": "#" },
    { "title": "Creative Tim", "imageUrl": "/partners/partner-creative-tim.webp", "link": "#" },
    { "title": "DigitalOcean", "imageUrl": "/partners/partner-digitalocean.webp", "link": "#" },
    { "title": "CIS", "imageUrl": "/partners/partner-cis.webp", "link": "#" },
    { "title": "Taskade", "imageUrl": "/partners/partner-taskade.webp", "link": "#" },
    { "title": "JetBrains", "imageUrl": "/partners/partner-jetbrains.webp", "link": "#" },
    { "title": "InVision", "imageUrl": "/partners/partner-invision.webp", "link": "#" },
    { "title": "GeeksforGeeks", "imageUrl": "/partners/partner-geeksforgeeks.webp", "link": "#" },
    { "title": "IBM", "imageUrl": "/partners/partner-ibm.webp", "link": "#" },
    { "title": "Hasura", "imageUrl": "/partners/partner-hasura.webp", "link": "#" },
    { "title": "HackerEarth", "imageUrl": "/partners/partner-hackerearth.webp", "link": "#" },
    { "title": "Orient Electric", "imageUrl": "/partners/partner-orient-electric.webp", "link": "#" },
    { "title": ".Tech Domains", "imageUrl": "/partners/partner-tech-domains.webp", "link": "#" },
    { "title": "Axure", "imageUrl": "/partners/partner-axure.webp", "link": "#" },
    { "title": "Sticker Mule", "imageUrl": "/partners/partner-sticker-mule.webp", "link": "#" },
    { "title": "Cosmos India", "imageUrl": "/partners/partner-cosmos-india.webp", "link": "#" },
    { "title": "Slang Labs", "imageUrl": "/partners/partner-slang-labs.webp", "link": "#" },
    { "title": "Sketch", "imageUrl": "/partners/partner-sketch.webp", "link": "#" },
    { "title": "Rosenfeld", "imageUrl": "/partners/partner-rosenfeld.webp", "link": "#" },
    { "title": "Glam Studios", "imageUrl": "/partners/partner-glam-studios.webp", "link": "#" },
    { "title": "EaseMyTrip", "imageUrl": "/partners/partner-easemytrip.webp", "link": "#" },
    { "title": "Into The Verse", "imageUrl": "/partners/partner-into-the-verse.webp", "link": "#" },
    { "title": "Nuclei", "imageUrl": "/partners/partner-nuclei.webp", "link": "#" },
    { "title": "HackerRank", "imageUrl": "/partners/partner-hackerrank.webp", "link": "#" },
    { "title": "Urban Jungle", "imageUrl": "/partners/partner-urban-jungle.webp", "link": "#" },
    { "title": "Judge0", "imageUrl": "/partners/partner-judge0.webp", "link": "#" },
    { "title": "ElevenLabs", "imageUrl": "/partners/partner-elevenlabs.webp", "link": "#" },
    { "title": "RunPod", "imageUrl": "/partners/partner-runpod.webp", "link": "#" },
    { "title": "Hey Hoku", "imageUrl": "/partners/partner-hey-hoku.webp", "link": "#" }
  ]
}
